otreeutils/__init__.py
otreeutils/pages.py
otreeutils/scripts.py
otreeutils/surveys.py
otreeutils/admin_extensions/__init__.py
otreeutils/admin_extensions/channels_consumers.py
otreeutils/admin_extensions/routing.py
otreeutils/admin_extensions/urls.py
otreeutils/admin_extensions/views.py
otreeutils/static/otreeutils/surveys.css
otreeutils/static/otreeutils/understanding.css
otreeutils/static/otreeutils/understanding.js
otreeutils/templates/otreeutils/ExtendedPage.html
otreeutils/templates/otreeutils/SurveyPage.html
otreeutils/templates/otreeutils/UnderstandingQuestionsPage.html
otreeutils/templates/otreeutils/admin/ExportIndexExtension.html
otreeutils/templates/otreeutils/admin/SessionDataExtension.html
otreeutils/templates/otreeutils/forms/radio_select_horizontal.html
otreeutils/templatetags/__init__.py
otreeutils/templatetags/otreeutils_tags.py
otreeutils-0.10.0.dist-info/LICENSE
otreeutils-0.10.0.dist-info/METADATA
otreeutils-0.10.0.dist-info/WHEEL
otreeutils-0.10.0.dist-info/top_level.txt
otreeutils-0.10.0.dist-info/RECORD
