Metadata-Version: 2.1
Name: otreeutils
Version: 0.10.0
Summary: Facilitate oTree experiment implementation with extensions for custom data models, surveys, understanding questions, timeout warnings and more.
Home-page: https://github.com/WZBSocialScienceCenter/otreeutils
Author: Markus Konrad
Author-email: markus.konrad@wzb.eu
License: Apache License 2.0
Project-URL: Bug Reports, https://github.com/WZBSocialScienceCenter/otreeutils/issues
Project-URL: Source, https://github.com/WZBSocialScienceCenter/otreeutils
Keywords: otree experiments social science finance economics development
Platform: UNKNOWN
Classifier: Development Status :: 4 - Beta
Classifier: Intended Audience :: Developers
Classifier: Environment :: Web Environment
Classifier: Framework :: Django
Classifier: License :: OSI Approved :: Apache Software License
Classifier: Operating System :: OS Independent
Classifier: Programming Language :: Python
Classifier: Programming Language :: Python :: 3
Classifier: Programming Language :: Python :: 3.7
Classifier: Programming Language :: Python :: 3.8
Classifier: Topic :: Internet :: WWW/HTTP
Classifier: Topic :: Internet :: WWW/HTTP :: Dynamic Content
Requires-Dist: otree (<4,>=3.3)
Provides-Extra: admin
Requires-Dist: pandas (<1.3,>=1.0) ; extra == 'admin'
Provides-Extra: all
Requires-Dist: pandas (<1.3,>=1.0) ; extra == 'all'
Requires-Dist: tox (<3.22,>=3.21.0) ; extra == 'all'
Requires-Dist: twine (<3.2,>=3.1.0) ; extra == 'all'
Provides-Extra: develop
Requires-Dist: tox (<3.22,>=3.21.0) ; extra == 'develop'
Requires-Dist: twine (<3.2,>=3.1.0) ; extra == 'develop'
